{
	"info": {
		"_postman_id": "4f6bf472-0a3f-452f-8c60-9451c927175f",
		"name": "bioAndes",
		"schema": "https://schema.getpostman.com/json/collection/v2.1.0/collection.json"
	},
	"item": [
		{
			"name": "Clases",
			"item": [
				{
					"name": "/api/clases",
					"request": {
						"method": "GET",
						"header": [],
						"body": {
							"mode": "raw",
							"raw": ""
						},
						"url": {
							"raw": "http://localhost:3000/api/clases",
							"protocol": "http",
							"host": [
								"localhost"
							],
							"port": "3000",
							"path": [
								"api",
								"clases"
							]
						}
					},
					"response": []
				},
				{
					"name": "/api/clases",
					"request": {
						"method": "POST",
						"header": [
							{
								"key": "Content-Type",
								"name": "Content-Type",
								"value": "application/json",
								"type": "text"
							}
						],
						"body": {
							"mode": "raw",
							"raw": "{\n    \"_id\": \"5c7c8cbe44f8b8283a5627cc\",\n    \"nombre\": \"nueva clase\"\n}"
						},
						"url": {
							"raw": "http://localhost:3000/api/clases",
							"protocol": "http",
							"host": [
								"localhost"
							],
							"port": "3000",
							"path": [
								"api",
								"clases"
							]
						}
					},
					"response": []
				},
				{
					"name": "/api/clases/:id",
					"request": {
						"method": "PUT",
						"header": [
							{
								"key": "Content-Type",
								"name": "Content-Type",
								"type": "text",
								"value": "application/json"
							}
						],
						"body": {
							"mode": "raw",
							"raw": "{\n    \"nombre\": \"mi clase\"\n}"
						},
						"url": {
							"raw": "http://localhost:3000/api/clases/5c7c8cbe44f8b8283a5627cc",
							"protocol": "http",
							"host": [
								"localhost"
							],
							"port": "3000",
							"path": [
								"api",
								"clases",
								"5c7c8cbe44f8b8283a5627cc"
							]
						}
					},
					"response": []
				},
				{
					"name": "/api/clases/:id",
					"request": {
						"method": "DELETE",
						"header": [],
						"body": {
							"mode": "raw",
							"raw": ""
						},
						"url": {
							"raw": "http://localhost:3000/api/clases/5c7c8cbe44f8b8283a5627cc",
							"protocol": "http",
							"host": [
								"localhost"
							],
							"port": "3000",
							"path": [
								"api",
								"clases",
								"5c7c8cbe44f8b8283a5627cc"
							]
						}
					},
					"response": []
				}
			]
		},
		{
			"name": "Colectores",
			"item": [
				{
					"name": "/api/colectores",
					"request": {
						"method": "GET",
						"header": [],
						"body": {
							"mode": "raw",
							"raw": ""
						},
						"url": {
							"raw": "http://localhost:3000/api/colectores",
							"protocol": "http",
							"host": [
								"localhost"
							],
							"port": "3000",
							"path": [
								"api",
								"colectores"
							]
						}
					},
					"response": []
				},
				{
					"name": "/api/colectores",
					"request": {
						"method": "POST",
						"header": [
							{
								"key": "Content-Type",
								"name": "Content-Type",
								"value": "application/json",
								"type": "text"
							}
						],
						"body": {
							"mode": "raw",
							"raw": "{\n    \"_id\": \"5c7c8e476b7e0628468feac6\",\n    \"nombre\": \"nuevo colector\"\n}"
						},
						"url": {
							"raw": "http://localhost:3000/api/colectores",
							"protocol": "http",
							"host": [
								"localhost"
							],
							"port": "3000",
							"path": [
								"api",
								"colectores"
							]
						}
					},
					"response": []
				},
				{
					"name": "/api/colectores/:id",
					"request": {
						"method": "PUT",
						"header": [
							{
								"key": "Content-Type",
								"name": "Content-Type",
								"value": "application/json",
								"type": "text"
							}
						],
						"body": {
							"mode": "raw",
							"raw": "{\n    \"nombre\": \"mi colector\"\n}"
						},
						"url": {
							"raw": "http://localhost:3000/api/colectores/5c7c8e476b7e0628468feac6",
							"protocol": "http",
							"host": [
								"localhost"
							],
							"port": "3000",
							"path": [
								"api",
								"colectores",
								"5c7c8e476b7e0628468feac6"
							]
						}
					},
					"response": []
				},
				{
					"name": "/api/colectores/:id",
					"request": {
						"method": "DELETE",
						"header": [],
						"body": {
							"mode": "raw",
							"raw": ""
						},
						"url": {
							"raw": "http://localhost:3000/api/colectores/5c7c8e476b7e0628468feac6",
							"protocol": "http",
							"host": [
								"localhost"
							],
							"port": "3000",
							"path": [
								"api",
								"colectores",
								"5c7c8e476b7e0628468feac6"
							]
						}
					},
					"response": []
				}
			]
		},
		{
			"name": "Especies",
			"item": [
				{
					"name": "/api/especies",
					"request": {
						"method": "GET",
						"header": [],
						"body": {
							"mode": "raw",
							"raw": ""
						},
						"url": {
							"raw": "http://localhost:3000/api/especies",
							"protocol": "http",
							"host": [
								"localhost"
							],
							"port": "3000",
							"path": [
								"api",
								"especies"
							]
						}
					},
					"response": []
				},
				{
					"name": "/api/especies",
					"request": {
						"method": "POST",
						"header": [
							{
								"key": "Content-Type",
								"name": "Content-Type",
								"value": "application/json",
								"type": "text"
							}
						],
						"body": {
							"mode": "raw",
							"raw": "{\n    \"_id\": \"5c7cbab41522b5392806a72f\",\n    \"nombre\": \"nueva especie\"\n}"
						},
						"url": {
							"raw": "http://localhost:3000/api/especies",
							"protocol": "http",
							"host": [
								"localhost"
							],
							"port": "3000",
							"path": [
								"api",
								"especies"
							]
						}
					},
					"response": []
				},
				{
					"name": "/api/especies/:id",
					"request": {
						"method": "PUT",
						"header": [
							{
								"key": "Content-Type",
								"name": "Content-Type",
								"value": "application/json",
								"type": "text"
							}
						],
						"body": {
							"mode": "raw",
							"raw": "{\n    \"nombre\": \"mi especie\"\n}"
						},
						"url": {
							"raw": "http://localhost:3000/api/especies/5c7cbab41522b5392806a72f",
							"protocol": "http",
							"host": [
								"localhost"
							],
							"port": "3000",
							"path": [
								"api",
								"especies",
								"5c7cbab41522b5392806a72f"
							]
						}
					},
					"response": []
				},
				{
					"name": "/api/especies/:id",
					"request": {
						"method": "DELETE",
						"header": [],
						"body": {
							"mode": "raw",
							"raw": ""
						},
						"url": {
							"raw": "http://localhost:3000/api/especies/5c7cbab41522b5392806a72f",
							"protocol": "http",
							"host": [
								"localhost"
							],
							"port": "3000",
							"path": [
								"api",
								"especies",
								"5c7cbab41522b5392806a72f"
							]
						}
					},
					"response": []
				}
			]
		},
		{
			"name": "Especimenes",
			"item": [
				{
					"name": "/api/especimenes",
					"request": {
						"method": "GET",
						"header": [],
						"body": {
							"mode": "raw",
							"raw": ""
						},
						"url": {
							"raw": "http://localhost:3000/api/especimenes",
							"protocol": "http",
							"host": [
								"localhost"
							],
							"port": "3000",
							"path": [
								"api",
								"especimenes"
							]
						}
					},
					"response": []
				},
				{
					"name": "/api/especimenes",
					"request": {
						"method": "POST",
						"header": [
							{
								"key": "Content-Type",
								"name": "Content-Type",
								"value": "application/json",
								"type": "text"
							}
						],
						"body": {
							"mode": "raw",
							"raw": "{\n\t\"_id\": \"5c7cbfb21d82d9399a15c099\",\n    \"colector\": \"5c7c75561c9d4400009cedd3\",\n    \"lugar\": \"5c7c71901c9d4400009cedd5\",\n    \"reino\": \"5c7c6d1f1c9d4400009cedc6\",\n    \"clase\": \"5c7c6d5d1c9d4400009cedc7\",\n    \"orden\": \"5c7c6e561c9d4400009cedc9\",\n    \"familia\": \"5c7c75081c9d4400009cedd6\",\n    \"genero\": \"5c7c752e1c9d4400009cedd7\",\n    \"especie\": \"5c7c75561c9d4400009cedd8\",\n    \"descripcion\": \"nuevo espécimen\",\n    \"ubicacion\": {\n        \"latitud\": 42.4242424,\n        \"longitud\": 42.4242424\n    }\n}"
						},
						"url": {
							"raw": "http://localhost:3000/api/especimenes",
							"protocol": "http",
							"host": [
								"localhost"
							],
							"port": "3000",
							"path": [
								"api",
								"especimenes"
							]
						}
					},
					"response": []
				},
				{
					"name": "/api/especimenes",
					"request": {
						"method": "PUT",
						"header": [
							{
								"key": "Content-Type",
								"name": "Content-Type",
								"value": "application/json",
								"type": "text"
							}
						],
						"body": {
							"mode": "raw",
							"raw": "{\n    \"colector\": \"5c7c75561c9d4400009cedd3\",\n    \"lugar\": \"5c7c71901c9d4400009cedd5\",\n    \"reino\": \"5c7c6d1f1c9d4400009cedc6\",\n    \"clase\": \"5c7c6d5d1c9d4400009cedc7\",\n    \"orden\": \"5c7c6e561c9d4400009cedc9\",\n    \"familia\": \"5c7c75081c9d4400009cedd6\",\n    \"genero\": \"5c7c752e1c9d4400009cedd7\",\n    \"especie\": \"5c7c75561c9d4400009cedd8\",\n    \"descripcion\": \"mi espécimen\",\n    \"ubicacion\": {\n        \"latitud\": 42.4242424,\n        \"longitud\": 42.4242424\n    }\n}"
						},
						"url": {
							"raw": "http://localhost:3000/api/especimenes/5c7cbfb21d82d9399a15c099",
							"protocol": "http",
							"host": [
								"localhost"
							],
							"port": "3000",
							"path": [
								"api",
								"especimenes",
								"5c7cbfb21d82d9399a15c099"
							]
						}
					},
					"response": []
				},
				{
					"name": "/api/especimenes",
					"request": {
						"method": "DELETE",
						"header": [],
						"body": {
							"mode": "raw",
							"raw": ""
						},
						"url": {
							"raw": "http://localhost:3000/api/especimenes/5c7cbfb21d82d9399a15c099",
							"protocol": "http",
							"host": [
								"localhost"
							],
							"port": "3000",
							"path": [
								"api",
								"especimenes",
								"5c7cbfb21d82d9399a15c099"
							]
						}
					},
					"response": []
				}
			]
		},
		{
			"name": "Familias",
			"item": [
				{
					"name": "/api/familias",
					"request": {
						"method": "GET",
						"header": [],
						"body": {
							"mode": "raw",
							"raw": ""
						},
						"url": {
							"raw": "http://localhost:3000/api/familias",
							"protocol": "http",
							"host": [
								"localhost"
							],
							"port": "3000",
							"path": [
								"api",
								"familias"
							]
						}
					},
					"response": []
				},
				{
					"name": "/api/familias",
					"request": {
						"method": "POST",
						"header": [
							{
								"key": "Content-Type",
								"name": "Content-Type",
								"value": "application/json",
								"type": "text"
							}
						],
						"body": {
							"mode": "raw",
							"raw": "{\n    \"_id\": \"5c7cb89b751d8a39020e554d\",\n    \"nombre\": \"nueva familia\"\n}"
						},
						"url": {
							"raw": "http://localhost:3000/api/familias",
							"protocol": "http",
							"host": [
								"localhost"
							],
							"port": "3000",
							"path": [
								"api",
								"familias"
							]
						}
					},
					"response": []
				},
				{
					"name": "/api/familias/:id",
					"request": {
						"method": "PUT",
						"header": [
							{
								"key": "Content-Type",
								"name": "Content-Type",
								"value": "application/json",
								"type": "text"
							}
						],
						"body": {
							"mode": "raw",
							"raw": "{\n    \"nombre\": \"mi familia\"\n}"
						},
						"url": {
							"raw": "http://localhost:3000/api/familias/5c7cb89b751d8a39020e554d",
							"protocol": "http",
							"host": [
								"localhost"
							],
							"port": "3000",
							"path": [
								"api",
								"familias",
								"5c7cb89b751d8a39020e554d"
							]
						}
					},
					"response": []
				},
				{
					"name": "/api/familias/:id",
					"request": {
						"method": "DELETE",
						"header": [],
						"body": {
							"mode": "raw",
							"raw": ""
						},
						"url": {
							"raw": "http://localhost:3000/api/familias/5c7cb89b751d8a39020e554d",
							"protocol": "http",
							"host": [
								"localhost"
							],
							"port": "3000",
							"path": [
								"api",
								"familias",
								"5c7cb89b751d8a39020e554d"
							]
						}
					},
					"response": []
				}
			]
		},
		{
			"name": "Generos",
			"item": [
				{
					"name": "/api/generos",
					"request": {
						"method": "GET",
						"header": [],
						"body": {
							"mode": "raw",
							"raw": ""
						},
						"url": {
							"raw": "http://localhost:3000/api/generos",
							"protocol": "http",
							"host": [
								"localhost"
							],
							"port": "3000",
							"path": [
								"api",
								"generos"
							]
						}
					},
					"response": []
				},
				{
					"name": "/api/generos",
					"request": {
						"method": "POST",
						"header": [
							{
								"key": "Content-Type",
								"name": "Content-Type",
								"value": "application/json",
								"type": "text"
							}
						],
						"body": {
							"mode": "raw",
							"raw": "{\n    \"_id\": \"5c7ca920afbc543097a23d9a\",\n    \"nombre\": \"nuevo genero\"\n}"
						},
						"url": {
							"raw": "http://localhost:3000/api/generos",
							"protocol": "http",
							"host": [
								"localhost"
							],
							"port": "3000",
							"path": [
								"api",
								"generos"
							]
						}
					},
					"response": []
				},
				{
					"name": "/api/generos/:id",
					"request": {
						"method": "PUT",
						"header": [
							{
								"key": "Content-Type",
								"name": "Content-Type",
								"value": "application/json",
								"type": "text"
							}
						],
						"body": {
							"mode": "raw",
							"raw": "{\n    \"nombre\": \"mi genero\"\n}"
						},
						"url": {
							"raw": "http://localhost:3000/api/generos/5c7ca920afbc543097a23d9a",
							"protocol": "http",
							"host": [
								"localhost"
							],
							"port": "3000",
							"path": [
								"api",
								"generos",
								"5c7ca920afbc543097a23d9a"
							]
						}
					},
					"response": []
				},
				{
					"name": "/api/ordenes/:id",
					"request": {
						"method": "DELETE",
						"header": [],
						"body": {
							"mode": "raw",
							"raw": ""
						},
						"url": {
							"raw": "http://localhost:3000/api/generos/5c7ca920afbc543097a23d9a",
							"protocol": "http",
							"host": [
								"localhost"
							],
							"port": "3000",
							"path": [
								"api",
								"generos",
								"5c7ca920afbc543097a23d9a"
							]
						}
					},
					"response": []
				}
			]
		},
		{
			"name": "Lugares",
			"item": [
				{
					"name": "/api/lugares",
					"request": {
						"method": "GET",
						"header": [],
						"body": {
							"mode": "raw",
							"raw": ""
						},
						"url": {
							"raw": "http://localhost:3000/api/lugares",
							"protocol": "http",
							"host": [
								"localhost"
							],
							"port": "3000",
							"path": [
								"api",
								"lugares"
							]
						}
					},
					"response": []
				},
				{
					"name": "/api/lugares",
					"request": {
						"method": "POST",
						"header": [
							{
								"key": "Content-Type",
								"name": "Content-Type",
								"value": "application/json",
								"type": "text"
							}
						],
						"body": {
							"mode": "raw",
							"raw": "{\n\t\"_id\": \"5c7cc644bd4cd43b7fbdd54a\",\n    \"pais\": \"nuevo pais\",\n    \"departamento\": \"nuevo departamento\",\n    \"municipio\": \"nuevo municipio\",\n    \"localidad\": \"nueva localidad\"\n}"
						},
						"url": {
							"raw": "http://localhost:3000/api/lugares",
							"protocol": "http",
							"host": [
								"localhost"
							],
							"port": "3000",
							"path": [
								"api",
								"lugares"
							]
						}
					},
					"response": []
				},
				{
					"name": "/api/lugares/:id",
					"request": {
						"method": "PUT",
						"header": [
							{
								"key": "Content-Type",
								"name": "Content-Type",
								"value": "application/json",
								"type": "text"
							}
						],
						"body": {
							"mode": "raw",
							"raw": "{\n    \"pais\": \"mi pais\",\n    \"departamento\": \"mi departamento\",\n    \"municipio\": \"mi municipio\",\n    \"localidad\": \"mi localidad\"\n}"
						},
						"url": {
							"raw": "http://localhost:3000/api/lugares/5c7cc644bd4cd43b7fbdd54a",
							"protocol": "http",
							"host": [
								"localhost"
							],
							"port": "3000",
							"path": [
								"api",
								"lugares",
								"5c7cc644bd4cd43b7fbdd54a"
							]
						}
					},
					"response": []
				},
				{
					"name": "/api/lugares/:id",
					"request": {
						"method": "DELETE",
						"header": [],
						"body": {
							"mode": "raw",
							"raw": ""
						},
						"url": {
							"raw": "http://localhost:3000/api/lugares/5c7cc644bd4cd43b7fbdd54a",
							"protocol": "http",
							"host": [
								"localhost"
							],
							"port": "3000",
							"path": [
								"api",
								"lugares",
								"5c7cc644bd4cd43b7fbdd54a"
							]
						}
					},
					"response": []
				}
			]
		},
		{
			"name": "Ordenes",
			"item": [
				{
					"name": "/api/ordenes",
					"request": {
						"method": "GET",
						"header": [],
						"body": {
							"mode": "raw",
							"raw": ""
						},
						"url": {
							"raw": "http://localhost:3000/api/ordenes",
							"protocol": "http",
							"host": [
								"localhost"
							],
							"port": "3000",
							"path": [
								"api",
								"ordenes"
							]
						}
					},
					"response": []
				},
				{
					"name": "/api/ordenes",
					"request": {
						"method": "POST",
						"header": [
							{
								"key": "Content-Type",
								"name": "Content-Type",
								"value": "application/json",
								"type": "text"
							}
						],
						"body": {
							"mode": "raw",
							"raw": "{\n    \"_id\": \"5c7c9129d986ec2950825e6c\",\n    \"nombre\": \"nueva orden\"\n}"
						},
						"url": {
							"raw": "http://localhost:3000/api/ordenes",
							"protocol": "http",
							"host": [
								"localhost"
							],
							"port": "3000",
							"path": [
								"api",
								"ordenes"
							]
						}
					},
					"response": []
				},
				{
					"name": "/api/ordenes/:id",
					"request": {
						"method": "PUT",
						"header": [
							{
								"key": "Content-Type",
								"name": "Content-Type",
								"value": "application/json",
								"type": "text"
							}
						],
						"body": {
							"mode": "raw",
							"raw": "{\n    \"nombre\": \"mi orden\"\n}"
						},
						"url": {
							"raw": "http://localhost:3000/api/ordenes/5c7c9129d986ec2950825e6c",
							"protocol": "http",
							"host": [
								"localhost"
							],
							"port": "3000",
							"path": [
								"api",
								"ordenes",
								"5c7c9129d986ec2950825e6c"
							]
						}
					},
					"response": []
				},
				{
					"name": "/api/ordenes Copy Copy",
					"request": {
						"method": "DELETE",
						"header": [],
						"body": {
							"mode": "raw",
							"raw": ""
						},
						"url": {
							"raw": "http://localhost:3000/api/ordenes/5c7c9129d986ec2950825e6c",
							"protocol": "http",
							"host": [
								"localhost"
							],
							"port": "3000",
							"path": [
								"api",
								"ordenes",
								"5c7c9129d986ec2950825e6c"
							]
						}
					},
					"response": []
				}
			]
		},
		{
			"name": "Reinos",
			"item": [
				{
					"name": "/api/reinos",
					"request": {
						"method": "GET",
						"header": [],
						"body": {
							"mode": "raw",
							"raw": ""
						},
						"url": {
							"raw": "http://localhost:3000/api/reinos",
							"protocol": "http",
							"host": [
								"localhost"
							],
							"port": "3000",
							"path": [
								"api",
								"reinos"
							]
						}
					},
					"response": []
				},
				{
					"name": "/api/reinos",
					"request": {
						"method": "POST",
						"header": [
							{
								"key": "Content-Type",
								"name": "Content-Type",
								"value": "application/json",
								"type": "text"
							}
						],
						"body": {
							"mode": "raw",
							"raw": "{\n    \"_id\": \"5c7c8a911d3b2d27fb91a40f\",\n    \"nombre\": \"nuevo reino\"\n}"
						},
						"url": {
							"raw": "http://localhost:3000/api/reinos",
							"protocol": "http",
							"host": [
								"localhost"
							],
							"port": "3000",
							"path": [
								"api",
								"reinos"
							]
						}
					},
					"response": []
				},
				{
					"name": "/api/reinos/:id",
					"request": {
						"method": "PUT",
						"header": [
							{
								"key": "Content-Type",
								"name": "Content-Type",
								"type": "text",
								"value": "application/json"
							}
						],
						"body": {
							"mode": "raw",
							"raw": "{\n    \"nombre\": \"mi reino\"\n}"
						},
						"url": {
							"raw": "http://localhost:3000/api/reinos/5c7c8a911d3b2d27fb91a40f",
							"protocol": "http",
							"host": [
								"localhost"
							],
							"port": "3000",
							"path": [
								"api",
								"reinos",
								"5c7c8a911d3b2d27fb91a40f"
							]
						}
					},
					"response": []
				},
				{
					"name": "/api/reinos/:id",
					"request": {
						"method": "DELETE",
						"header": [],
						"body": {
							"mode": "raw",
							"raw": ""
						},
						"url": {
							"raw": "http://localhost:3000/api/reinos/5c7c8a911d3b2d27fb91a40f",
							"protocol": "http",
							"host": [
								"localhost"
							],
							"port": "3000",
							"path": [
								"api",
								"reinos",
								"5c7c8a911d3b2d27fb91a40f"
							]
						}
					},
					"response": []
				}
			]
		}
	]
}